models_lib/__init__.py
models_lib/models.py
models_lib-0.1.3.dist-info/METADATA
models_lib-0.1.3.dist-info/WHEEL
models_lib-0.1.3.dist-info/top_level.txt
models_lib-0.1.3.dist-info/RECORD
